whatdeps/__init__.py
whatdeps/__main__.py
whatdeps/cli.py
whatdeps/inspector.py
whatdeps/models.py
whatdeps/parser.py
whatdeps/reporter.py
whatdeps/utils.py
whatdeps-0.1.0.post1.dist-info/METADATA
whatdeps-0.1.0.post1.dist-info/WHEEL
whatdeps-0.1.0.post1.dist-info/entry_points.txt
whatdeps-0.1.0.post1.dist-info/licenses/LICENSE
whatdeps-0.1.0.post1.dist-info/RECORD
